Workbook

Sheet Instructions
B2: Excel Skills Test
B4: Overview
B5: The "Order Data" tab contains 12 months of wholesale order-line data for a consumer packaged goods company. Each row is one line item on a purchase order from a retail customer. Your task is to summarize this data using PivotTables and a VLOOKUP, and answer four questions. A "Customer Directory" reference tab is also included. Please record your screen while you work so we can see your process.
B7: Time Target
B8: 5 to 10 minutes.
B10: Column Definitions
B11: Order ID: Unique identifier for the purchase order.
B12: Order Date: Date the retailer placed the order.
B13: Customer: Retail account name.
B14: Region: Geographic region the customer is assigned to.
B15: Product Category: High-level product grouping.
B16: SKU: Individual product identifier.
... B40: When you are finished, save the file and submit it along with your screen recording. Good luck!

Sheet Customer Directory
A1: Customer | B1: Account Tier | C1: Sales Rep | D1: Payment Terms (Days)
A2: Walmart | B2: Strategic | C2: Karen Olsen | D2: 45
A3: Target | B3: Strategic | C3: Karen Olsen | D3: 45
A4: Kroger | B4: Key | C4: James Peralta | D4: 30
A5: Costco | B5: Strategic | C5: Karen Olsen | D5: 45
A6: Sam's Club | B6: Key | C6: James Peralta | D6: 30
A7: Meijer | B7: Growth | C7: David Cho | D7: 30
A8: HEB | B8: Growth | C8: Maria Santos | D8: 15
A9: Publix | B9: Growth | C9: Maria Santos | D9: 15

Sheet Order Data
A1: Order ID | B1: Order Date | C1: Customer | D1: Region | E1: Product Category | F1: SKU | G1: Units | H1: Unit Price | I1: Line Revenue
A2: PO-1000 | B2: 45670 | C2: Costco | D2: West | E2: Household | F2: HH-300 | G2: 1558 | H2: 5.99 | I2: =G2*H2 -> 9332.42
A3: PO-1000 | B3: 45670 | C3: Costco | D3: West | E3: Snacks | F3: SNK-100 | G3: 1435 | H3: 3.49 | I3: =G3*H3 -> 5008.15
A4: PO-1000 | B4: 45670 | C4: Costco | D4: West | E4: Personal Care | F4: PC-402 | G4: 1877 | H4: 3.79 | I4: =G4*H4 -> 7113.83
A5: PO-1001 | B5: 45960 | C5: Kroger | D5: East | E5: Snacks | F5: SNK-100 | G5: 497 | H5: 3.49 | I5: =G5*H5 -> 1734.53
A6: PO-1001 | B6: 45960 | C6: Kroger | D6: East | E6: Personal Care | F6: PC-400 | G6: 1084 | H6: 6.29 | I6: =G6*H6 -> 6818.36
A7: PO-1002 | B7: 45945 | C7: Kroger | D7: East | E7: Personal Care | F7: PC-400 | G7: 969 | H7: 6.29 | I7: =G7*H7 -> 6095.01
A8: PO-1003 | B8: 45661 | C8: Kroger | D8: East | E8: Personal Care | F8: PC-401 | G8: 619 | H8: 8.99 | I8: =G8*H8 -> 5564.81
A9: PO-1004 | B9: 45830 | C9: Walmart | D9: Central | E9: Snacks | F9: SNK-101 | G9: 248 | H9: 4.29 | I9: =G9*H9 -> 1063.92
A10: PO-1005 | B10: 45834 | C10: Target | D10: Central | E10: Household | F10: HH-302 | G10: 305 | H10: 4.49 | I10: =G10*H10 -> 1369.45
A11: PO-1005 | B11: 45834 | C11: Target | D11: Central | E11: Snacks | F11: SNK-101 | G11: 211 | H11: 4.29 | I11: =G11*H11 -> 905.19
A12: PO-1005 | B12: 45834 | C12: Target | D12: Central | E12: Beverages | F12: BEV-202 | G12: 650 | H12: 3.19 | I12: =G12*H12 -> 2073.5
A13: PO-1006 | B13: 45974 | C13: Meijer | D13: East | E13: Beverages | F13: BEV-200 | G13: 143 | H13: 1.89 | I13: =G13*H13 -> 270.27
... A161: PO-1079 | B161: 45784 | C161: Sam's Club | D161: Central | E161: Snacks | F161: SNK-102 | G161: 362 | H161: 2.99 | I161: =G161*H161 -> 1082.38

Sheet Task 1

Sheet Task 2

Sheet Task 3

Sheet Task 4
A1: Customer | B1: Sales Rep | C1: total revenue
A2: =VLOOKUP('Customer Directory'!A2,'Customer Directory'!$A$2:$D$9,1,0) -> Walmart | B2: =VLOOKUP('Customer Directory'!C2,'Customer Directory'!C2:D9,1,0) -> Karen Olsen | C2: =VLOOKUP(A2, 'Task 1'!$A$2:$B$9, 2, FALSE) -> 200370.44
A3: =VLOOKUP('Customer Directory'!A3,'Customer Directory'!A3:D10,1,0) -> Target | B3: =VLOOKUP('Customer Directory'!C3,'Customer Directory'!C3:D10,1,0) -> Karen Olsen | C3: =VLOOKUP(A3, 'Task 1'!$A$2:$B$9, 2, FALSE) -> 175288.49
A4: =VLOOKUP('Customer Directory'!A4,'Customer Directory'!A4:D11,1,0) -> Kroger | B4: =VLOOKUP('Customer Directory'!C4,'Customer Directory'!C4:D11,1,0) -> James Peralta | C4: =VLOOKUP(A4, 'Task 1'!$A$2:$B$9, 2, FALSE) -> 108722.51
A5: =VLOOKUP('Customer Directory'!A5,'Customer Directory'!A5:D12,1,0) -> Costco | B5: =VLOOKUP('Customer Directory'!C5,'Customer Directory'!C5:D12,1,0) -> Karen Olsen | C5: =VLOOKUP(A5, 'Task 1'!$A$2:$B$9, 2, FALSE) -> 83275.99
A6: =VLOOKUP('Customer Directory'!A6,'Customer Directory'!A6:D13,1,0) -> Sam's Club | B6: =VLOOKUP('Customer Directory'!C6,'Customer Directory'!C6:D13,1,0) -> James Peralta | C6: =VLOOKUP(A6, 'Task 1'!$A$2:$B$9, 2, FALSE) -> 39319.75
A7: =VLOOKUP('Customer Directory'!A7,'Customer Directory'!A7:D14,1,0) -> Meijer | B7: =VLOOKUP('Customer Directory'!C7,'Customer Directory'!C7:D14,1,0) -> David Cho | C7: =VLOOKUP(A7, 'Task 1'!$A$2:$B$9, 2, FALSE) -> 16971.26
A8: =VLOOKUP('Customer Directory'!A8,'Customer Directory'!A8:D15,1,0) -> HEB | B8: =VLOOKUP('Customer Directory'!C8,'Customer Directory'!C8:D15,1,0) -> Maria Santos | C8: =VLOOKUP(A8, 'Task 1'!$A$2:$B$9, 2, FALSE) -> 54528.77
A9: =VLOOKUP('Customer Directory'!A9,'Customer Directory'!A9:D16,1,0) -> Publix | B9: =VLOOKUP('Customer Directory'!C9,'Customer Directory'!C9:D16,1,0) -> Maria Santos | C9: =VLOOKUP(A9, 'Task 1'!$A$2:$B$9, 2, FALSE) -> 24931.81

Sheet Task 4.1
